.pre-commit-config.yaml
CHANGES.md
CONTRIBUTORS.md
DEVELOP.md
LICENSE.GPL
LICENSE.md
MANIFEST.in
README.md
setup.cfg
setup.py
src/collective/__init__.py
src/collective.icecream.egg-info/PKG-INFO
src/collective.icecream.egg-info/SOURCES.txt
src/collective.icecream.egg-info/dependency_links.txt
src/collective.icecream.egg-info/entry_points.txt
src/collective.icecream.egg-info/namespace_packages.txt
src/collective.icecream.egg-info/not-zip-safe
src/collective.icecream.egg-info/requires.txt
src/collective.icecream.egg-info/top_level.txt
src/collective/icecream/__init__.py
src/collective/icecream/configure.zcml