Metadata-Version: 2.1
Name: collective.icecream
Version: 1.0.0a1
Summary: An addon for Plone that allow you debug your code using the icecream package
Home-page: https://github.com/collective/collective.icecream
Author: ale-rt
Author-email: alessandro.pisa@gmail.com
License: GPL version 2
Project-URL: PyPI, https://pypi.org/project/collective.icecream/
Project-URL: Source, https://github.com/collective/collective.icecream
Project-URL: Tracker, https://github.com/collective/collective.icecream/issues
Keywords: Python Plone CMS
Classifier: Development Status :: 3 - Alpha
Classifier: Environment :: Web Environment
Classifier: Framework :: Plone
Classifier: Framework :: Plone :: Addon
Classifier: Framework :: Plone :: 5.2
Classifier: Framework :: Plone :: 6.0
Classifier: Programming Language :: Python
Classifier: Programming Language :: Python :: 3.8
Classifier: Programming Language :: Python :: 3.9
Classifier: Programming Language :: Python :: 3.10
Classifier: Programming Language :: Python :: 3.11
Classifier: Operating System :: OS Independent
Classifier: License :: OSI Approved :: GNU General Public License v2 (GPLv2)
Requires-Python: >=3.8
License-File: LICENSE.GPL
License-File: LICENSE.md
Requires-Dist: setuptools
Requires-Dist: plone.api
Requires-Dist: icecream
Provides-Extra: test
Requires-Dist: plone.app.testing; extra == "test"
